[{"deploymentName":"Tacoma","deviceFriendlyName":"Crescent Heights Elementary School","msrDeviceNbr":"2189","readingDateTimeUTC":"2022-05-10 17:24:13","readingDateTimeLocal":"2022-05-10 10:24:13","latitude":47.29472222,"longitude":-122.4,"cellTowerAddress":"","tempC":17.335205078125,"humidity":49.6734619140625,"pressure":100709.8203125,"pM25":3.2532246112823486,"pM10":4.039681911468506,"pM1":2.4770331382751465,"vBattery":4.167655944824219,"cellSignal":-100,"fwVersion":"","aqi":13,"aqiLabel":"Good","calibratedPM25":3.2532246112823486,"calibrationVersion":"None"},{"deploymentName":"Tacoma","deviceFriendlyName":"Crescent Heights Elementary School","msrDeviceNbr":"2189","readingDateTimeUTC":"2022-05-10 17:04:01","readingDateTimeLocal":"2022-05-10 10:04:01","latitude":47.29472222,"longitude":-122.4,"cellTowerAddress":"","tempC":15.474014282226562,"humidity":47.265625,"pressure":100699.265625,"pM25":0.7052474021911621,"pM10":0.7052469253540039,"pM1":0.6669245958328247,"vBattery":4.170312404632568,"cellSignal":-100,"fwVersion":"","aqi":2,"aqiLabel":"Good","calibratedPM25":0.7052474021911621,"calibrationVersion":"None"},{"deploymentName":"Tacoma","deviceFriendlyName":"Crescent Heights Elementary School","msrDeviceNbr":"2189","readingDateTimeUTC":"2022-05-10 16:43:49","readingDateTimeLocal":"2022-05-10 09:43:49","latitude":47.29472222,"longitude":-122.4,"cellTowerAddress":"","tempC":18.579559326171875,"humidity":43.39752197265625,"pressure":100683.7578125,"pM25":2.432149648666382,"pM10":3.985191583633423,"pM1":1.1163121461868286,"vBattery":4.168749809265137,"cellSignal":-100,"fwVersion":"","aqi":10,"aqiLabel":"Good","calibratedPM25":2.432149648666382,"calibrationVersion":"None"},{"deploymentName":"Tacoma","deviceFriendlyName":"Crescent Heights Elementary School","msrDeviceNbr":"2189","readingDateTimeUTC":"2022-05-10 16:23:37","readingDateTimeLocal":"2022-05-10 09:23:37","latitude":47.29472222,"longitude":-122.4,"cellTowerAddress":"","tempC":19.33258056640625,"humidity":44.2718505859375,"pressure":100688.109375,"pM25":1.3474034070968628,"pM10":1.3474024534225464,"pM1":1.274186134338379,"vBattery":4.1640625,"cellSignal":-100,"fwVersion":"","aqi":5,"aqiLabel":"Good","calibratedPM25":1.3474034070968628,"calibrationVersion":"None"},{"deploymentName":"Tacoma","deviceFriendlyName":"Crescent Heights Elementary School","msrDeviceNbr":"2189","readingDateTimeUTC":"2022-05-10 16:03:25","readingDateTimeLocal":"2022-05-10 09:03:25","latitude":47.29472222,"longitude":-122.4,"cellTowerAddress":"","tempC":18.408660888671875,"humidity":48.98529052734375,"pressure":100685.6015625,"pM25":1.3478058576583862,"pM10":1.3478049039840698,"pM1":1.274566650390625,"vBattery":4.163749694824219,"cellSignal":-100,"fwVersion":"","aqi":5,"aqiLabel":"Good","calibratedPM25":1.3478058576583862,"calibrationVersion":"None"},{"deploymentName":"Tacoma","deviceFriendlyName":"Crescent Heights Elementary School","msrDeviceNbr":"2189","readingDateTimeUTC":"2022-05-10 15:43:14","readingDateTimeLocal":"2022-05-10 08:43:14","latitude":47.29472222,"longitude":-122.4,"cellTowerAddress":"","tempC":17.746429443359375,"humidity":47.332763671875,"pressure":100661.953125,"pM25":1.5392118692398071,"pM10":2.413654327392578,"pM1":0.789101243019104,"vBattery":4.166249752044678,"cellSignal":-100,"fwVersion":"","aqi":6,"aqiLabel":"Good","calibratedPM25":1.5392118692398071,"calibrationVersion":"None"},{"deploymentName":"Tacoma","deviceFriendlyName":"Crescent Heights Elementary School","msrDeviceNbr":"2189","readingDateTimeUTC":"2022-05-10 15:23:02","readingDateTimeLocal":"2022-05-10 08:23:02","latitude":47.29472222,"longitude":-122.4,"cellTowerAddress":"","tempC":16.718368530273438,"humidity":53.607177734375,"pressure":100644.6953125,"pM25":0.6697809100151062,"pM10":0.669780433177948,"pM1":0.6333853006362915,"vBattery":4.165156364440918,"cellSignal":-100,"fwVersion":"","aqi":2,"aqiLabel":"Good","calibratedPM25":0.6697809100151062,"calibrationVersion":"None"},{"deploymentName":"Tacoma","deviceFriendlyName":"Crescent Heights Elementary School","msrDeviceNbr":"2189","readingDateTimeUTC":"2022-05-10 15:02:50","readingDateTimeLocal":"2022-05-10 08:02:50","latitude":47.29472222,"longitude":-122.4,"cellTowerAddress":"","tempC":14.790420532226562,"humidity":57.32421875,"pressure":100626.3828125,"pM25":1.9072084426879883,"pM10":1.9072071313858032,"pM1":1.8035715818405151,"vBattery":4.165468692779541,"cellSignal":-100,"fwVersion":"","aqi":7,"aqiLabel":"Good","calibratedPM25":1.9072084426879883,"calibrationVersion":"None"},{"deploymentName":"Tacoma","deviceFriendlyName":"Crescent Heights Elementary School","msrDeviceNbr":"2189","readingDateTimeUTC":"2022-05-10 14:42:38","readingDateTimeLocal":"2022-05-10 07:42:38","latitude":47.29472222,"longitude":-122.4,"cellTowerAddress":"","tempC":12.819747924804688,"humidity":64.4805908203125,"pressure":100600.484375,"pM25":5.87809419631958,"pM10":10.011091232299805,"pM1":2.408653974533081,"vBattery":4.167500019073486,"cellSignal":-100,"fwVersion":"","aqi":24,"aqiLabel":"Good","calibratedPM25":5.87809419631958,"calibrationVersion":"None"},{"deploymentName":"Tacoma","deviceFriendlyName":"Crescent Heights Elementary School","msrDeviceNbr":"2189","readingDateTimeUTC":"2022-05-10 14:22:26","readingDateTimeLocal":"2022-05-10 07:22:26","latitude":47.29472222,"longitude":-122.4,"cellTowerAddress":"","tempC":9.925155639648438,"humidity":70.95947265625,"pressure":100581.7890625,"pM25":1.3421947956085205,"pM10":1.9280275106430054,"pM1":0.8227580785751343,"vBattery":4.172968864440918,"cellSignal":-100,"fwVersion":"","aqi":5,"aqiLabel":"Good","calibratedPM25":1.3421947956085205,"calibrationVersion":"None"},{"deploymentName":"Tacoma","deviceFriendlyName":"Crescent Heights Elementary School","msrDeviceNbr":"2189","readingDateTimeUTC":"2022-05-10 14:02:15","readingDateTimeLocal":"2022-05-10 07:02:15","latitude":47.29472222,"longitude":-122.4,"cellTowerAddress":"","tempC":8.061294555664062,"humidity":72.09320068359375,"pressure":100577.2578125,"pM25":1.450771689414978,"pM10":2.149252414703369,"pM1":0.8395794630050659,"vBattery":4.165625095367432,"cellSignal":-100,"fwVersion":"","aqi":6,"aqiLabel":"Good","calibratedPM25":1.450771689414978,"calibrationVersion":"None"},{"deploymentName":"Tacoma","deviceFriendlyName":"Crescent Heights Elementary School","msrDeviceNbr":"2189","readingDateTimeUTC":"2022-05-10 13:42:03","readingDateTimeLocal":"2022-05-10 06:42:03","latitude":47.29472222,"longitude":-122.4,"cellTowerAddress":"","tempC":7.62603759765625,"humidity":72.83172607421875,"pressure":100542.34375,"pM25":3.509141683578491,"pM10":5.672101974487305,"pM1":1.669922947883606,"vBattery":4.163749694824219,"cellSignal":-100,"fwVersion":"","aqi":14,"aqiLabel":"Good","calibratedPM25":3.509141683578491,"calibrationVersion":"None"},{"deploymentName":"Tacoma","deviceFriendlyName":"Crescent Heights Elementary School","msrDeviceNbr":"2189","readingDateTimeUTC":"2022-05-10 13:21:51","readingDateTimeLocal":"2022-05-10 06:21:51","latitude":47.29472222,"longitude":-122.4,"cellTowerAddress":"","tempC":7.28424072265625,"humidity":74.36676025390625,"pressure":100522.359375,"pM25":4.4226765632629395,"pM10":6.243635177612305,"pM1":2.794480085372925,"vBattery":4.162499904632568,"cellSignal":-100,"fwVersion":"","aqi":18,"aqiLabel":"Good","calibratedPM25":4.4226765632629395,"calibrationVersion":"None"},{"deploymentName":"Tacoma","deviceFriendlyName":"Crescent Heights Elementary School","msrDeviceNbr":"2189","readingDateTimeUTC":"2022-05-10 13:01:39","readingDateTimeLocal":"2022-05-10 06:01:39","latitude":47.29472222,"longitude":-122.4,"cellTowerAddress":"","tempC":7.1907806396484375,"humidity":74.9176025390625,"pressure":100506.5390625,"pM25":1.4447945356369019,"pM10":1.4447935819625854,"pM1":1.3662850856781006,"vBattery":4.161874771118164,"cellSignal":-100,"fwVersion":"","aqi":6,"aqiLabel":"Good","calibratedPM25":1.4447945356369019,"calibrationVersion":"None"},{"deploymentName":"Tacoma","deviceFriendlyName":"Crescent Heights Elementary School","msrDeviceNbr":"2189","readingDateTimeUTC":"2022-05-10 12:41:28","readingDateTimeLocal":"2022-05-10 05:41:28","latitude":47.29472222,"longitude":-122.4,"cellTowerAddress":"","tempC":7.0679473876953125,"humidity":74.957275390625,"pressure":100490.75,"pM25":3.9164137840270996,"pM10":5.940752029418945,"pM1":2.1607186794281006,"vBattery":4.163906097412109,"cellSignal":-100,"fwVersion":"","aqi":16,"aqiLabel":"Good","calibratedPM25":3.9164137840270996,"calibrationVersion":"None"},{"deploymentName":"Tacoma","deviceFriendlyName":"Crescent Heights Elementary School","msrDeviceNbr":"2189","readingDateTimeUTC":"2022-05-10 12:21:16","readingDateTimeLocal":"2022-05-10 05:21:16","latitude":47.29472222,"longitude":-122.4,"cellTowerAddress":"","tempC":6.755523681640625,"humidity":75.39825439453125,"pressure":100472.1484375,"pM25":7.747797966003418,"pM10":13.777307510375977,"pM1":2.731302499771118,"vBattery":4.164218425750732,"cellSignal":-100,"fwVersion":"","aqi":32,"aqiLabel":"Good","calibratedPM25":7.747797966003418,"calibrationVersion":"None"},{"deploymentName":"Tacoma","deviceFriendlyName":"Crescent Heights Elementary School","msrDeviceNbr":"2189","readingDateTimeUTC":"2022-05-10 12:01:05","readingDateTimeLocal":"2022-05-10 05:01:05","latitude":47.29472222,"longitude":-122.4,"cellTowerAddress":"","tempC":6.8169403076171875,"humidity":75.20751953125,"pressure":100453.1484375,"pM25":2.615161895751953,"pM10":3.787933588027954,"pM1":1.5792096853256226,"vBattery":4.163280963897705,"cellSignal":-100,"fwVersion":"","aqi":10,"aqiLabel":"Good","calibratedPM25":2.615161895751953,"calibrationVersion":"None"},{"deploymentName":"Tacoma","deviceFriendlyName":"Crescent Heights Elementary School","msrDeviceNbr":"2189","readingDateTimeUTC":"2022-05-10 11:40:54","readingDateTimeLocal":"2022-05-10 04:40:54","latitude":47.29472222,"longitude":-122.4,"cellTowerAddress":"","tempC":6.8169403076171875,"humidity":75.29754638671875,"pressure":100445.2578125,"pM25":3.7108256816864014,"pM10":3.7108230590820312,"pM1":3.509181022644043,"vBattery":4.163593769073486,"cellSignal":-100,"fwVersion":"","aqi":15,"aqiLabel":"Good","calibratedPM25":0,"calibrationVersion":""},{"deploymentName":"Tacoma","deviceFriendlyName":"Crescent Heights Elementary School","msrDeviceNbr":"2189","readingDateTimeUTC":"2022-05-10 11:20:42","readingDateTimeLocal":"2022-05-10 04:20:42","latitude":47.29472222,"longitude":-122.4,"cellTowerAddress":"","tempC":6.8169403076171875,"humidity":75.57373046875,"pressure":100432.359375,"pM25":2.5347392559051514,"pM10":3.6928870677948,"pM1":1.5143033266067505,"vBattery":4.164843559265137,"cellSignal":-100,"fwVersion":"","aqi":10,"aqiLabel":"Good","calibratedPM25":0,"calibrationVersion":""},{"deploymentName":"Tacoma","deviceFriendlyName":"Crescent Heights Elementary School","msrDeviceNbr":"2189","readingDateTimeUTC":"2022-05-10 11:00:30","readingDateTimeLocal":"2022-05-10 04:00:30","latitude":47.29472222,"longitude":-122.4,"cellTowerAddress":"","tempC":6.755523681640625,"humidity":74.9542236328125,"pressure":100415.5859375,"pM25":4.1432342529296875,"pM10":5.70335054397583,"pM1":2.729027271270752,"vBattery":4.163906097412109,"cellSignal":-100,"fwVersion":"","aqi":17,"aqiLabel":"Good","calibratedPM25":0,"calibrationVersion":""},{"deploymentName":"Tacoma","deviceFriendlyName":"Crescent Heights Elementary School","msrDeviceNbr":"2189","readingDateTimeUTC":"2022-05-10 10:40:19","readingDateTimeLocal":"2022-05-10 03:40:19","latitude":47.29472222,"longitude":-122.4,"cellTowerAddress":"","tempC":6.8703460693359375,"humidity":74.04937744140625,"pressure":100401.5859375,"pM25":1.4664876461029053,"pM10":1.4664866924285889,"pM1":1.3867993354797363,"vBattery":4.165781021118164,"cellSignal":-100,"fwVersion":"","aqi":6,"aqiLabel":"Good","calibratedPM25":0,"calibrationVersion":""},{"deploymentName":"Tacoma","deviceFriendlyName":"Crescent Heights Elementary School","msrDeviceNbr":"2189","readingDateTimeUTC":"2022-05-10 09:59:55","readingDateTimeLocal":"2022-05-10 02:59:55","latitude":47.29472222,"longitude":-122.4,"cellTowerAddress":"","tempC":7.36968994140625,"humidity":73.2208251953125,"pressure":100375.2421875,"pM25":2.1091558933258057,"pM10":2.7744975090026855,"pM1":1.4874439239501953,"vBattery":4.167031288146973,"cellSignal":-100,"fwVersion":"","aqi":8,"aqiLabel":"Good","calibratedPM25":0,"calibrationVersion":""},{"deploymentName":"Tacoma","deviceFriendlyName":"Crescent Heights Elementary School","msrDeviceNbr":"2189","readingDateTimeUTC":"2022-05-10 09:39:43","readingDateTimeLocal":"2022-05-10 02:39:43","latitude":47.29472222,"longitude":-122.4,"cellTowerAddress":"","tempC":7.556610107421875,"humidity":72.81494140625,"pressure":100351.7265625,"pM25":3.08319091796875,"pM10":4.247890472412109,"pM1":2.0279576778411865,"vBattery":4.166093826293945,"cellSignal":-100,"fwVersion":"","aqi":12,"aqiLabel":"Good","calibratedPM25":0,"calibrationVersion":""},{"deploymentName":"Tacoma","deviceFriendlyName":"Crescent Heights Elementary School","msrDeviceNbr":"2189","readingDateTimeUTC":"2022-05-10 09:19:31","readingDateTimeLocal":"2022-05-10 02:19:31","latitude":47.29472222,"longitude":-122.4,"cellTowerAddress":"","tempC":7.556610107421875,"humidity":71.3043212890625,"pressure":100350.734375,"pM25":1.8525723218917847,"pM10":2.9880740642547607,"pM1":0.8864640593528748,"vBattery":4.168124675750732,"cellSignal":-100,"fwVersion":"","aqi":7,"aqiLabel":"Good","calibratedPM25":0,"calibrationVersion":""},{"deploymentName":"Tacoma","deviceFriendlyName":"Crescent Heights Elementary School","msrDeviceNbr":"2189","readingDateTimeUTC":"2022-05-10 08:59:19","readingDateTimeLocal":"2022-05-10 01:59:19","latitude":47.29472222,"longitude":-122.4,"cellTowerAddress":"","tempC":7.7515411376953125,"humidity":71.26312255859375,"pressure":100341.4765625,"pM25":3.652559280395508,"pM10":4.653384208679199,"pM1":2.6912856101989746,"vBattery":4.166249752044678,"cellSignal":-100,"fwVersion":"","aqi":15,"aqiLabel":"Good","calibratedPM25":0,"calibrationVersion":""},{"deploymentName":"Tacoma","deviceFriendlyName":"Crescent Heights Elementary School","msrDeviceNbr":"2189","readingDateTimeUTC":"2022-05-10 08:39:08","readingDateTimeLocal":"2022-05-10 01:39:08","latitude":47.29472222,"longitude":-122.4,"cellTowerAddress":"","tempC":7.930450439453125,"humidity":71.014404296875,"pressure":100335.21875,"pM25":1.4656909704208374,"pM10":1.465690016746521,"pM1":1.386046051979065,"vBattery":4.167812347412109,"cellSignal":-100,"fwVersion":"","aqi":6,"aqiLabel":"Good","calibratedPM25":0,"calibrationVersion":""},{"deploymentName":"Tacoma","deviceFriendlyName":"Crescent Heights Elementary School","msrDeviceNbr":"2189","readingDateTimeUTC":"2022-05-10 08:18:56","readingDateTimeLocal":"2022-05-10 01:18:56","latitude":47.29472222,"longitude":-122.4,"cellTowerAddress":"","tempC":8.189468383789062,"humidity":69.81658935546875,"pressure":100319.609375,"pM25":2.0862879753112793,"pM10":2.0862865447998047,"pM1":1.9729201793670654,"vBattery":4.170312404632568,"cellSignal":-100,"fwVersion":"","aqi":8,"aqiLabel":"Good","calibratedPM25":0,"calibrationVersion":""},{"deploymentName":"Tacoma","deviceFriendlyName":"Crescent Heights Elementary School","msrDeviceNbr":"2189","readingDateTimeUTC":"2022-05-10 07:58:44","readingDateTimeLocal":"2022-05-10 00:58:44","latitude":47.29472222,"longitude":-122.4,"cellTowerAddress":"","tempC":8.686141967773438,"humidity":68.328857421875,"pressure":100307.7265625,"pM25":3.248490571975708,"pM10":3.248488426208496,"pM1":3.0719690322875977,"vBattery":4.169531345367432,"cellSignal":-100,"fwVersion":"","aqi":13,"aqiLabel":"Good","calibratedPM25":0,"calibrationVersion":""},{"deploymentName":"Tacoma","deviceFriendlyName":"Crescent Heights Elementary School","msrDeviceNbr":"2189","readingDateTimeUTC":"2022-05-10 07:38:32","readingDateTimeLocal":"2022-05-10 00:38:32","latitude":47.29472222,"longitude":-122.4,"cellTowerAddress":"","tempC":8.86505126953125,"humidity":67.3431396484375,"pressure":100284.671875,"pM25":5.340446949005127,"pM10":6.785126209259033,"pM1":3.949162721633911,"vBattery":4.169843673706055,"cellSignal":-100,"fwVersion":"","aqi":22,"aqiLabel":"Good","calibratedPM25":0,"calibrationVersion":""},{"deploymentName":"Tacoma","deviceFriendlyName":"Crescent Heights Elementary School","msrDeviceNbr":"2189","readingDateTimeUTC":"2022-05-10 07:18:21","readingDateTimeLocal":"2022-05-10 00:18:21","latitude":47.29472222,"longitude":-122.4,"cellTowerAddress":"","tempC":9.52728271484375,"humidity":67.19818115234375,"pressure":100274.6484375,"pM25":1.5808640718460083,"pM10":1.5808629989624023,"pM1":1.4949606657028198,"vBattery":4.170156002044678,"cellSignal":-100,"fwVersion":"","aqi":6,"aqiLabel":"Good","calibratedPM25":0,"calibrationVersion":""},{"deploymentName":"Tacoma","deviceFriendlyName":"Crescent Heights Elementary School","msrDeviceNbr":"2189","readingDateTimeUTC":"2022-05-10 06:58:09","readingDateTimeLocal":"2022-05-09 23:58:09","latitude":47.29472222,"longitude":-122.4,"cellTowerAddress":"","tempC":9.503250122070312,"humidity":66.4520263671875,"pressure":100259.984375,"pM25":0.9918416738510132,"pM10":0.9918410181999207,"pM1":0.9379454851150513,"vBattery":4.170312404632568,"cellSignal":-99,"fwVersion":"","aqi":4,"aqiLabel":"Good","calibratedPM25":0,"calibrationVersion":""},{"deploymentName":"Tacoma","deviceFriendlyName":"Crescent Heights Elementary School","msrDeviceNbr":"2189","readingDateTimeUTC":"2022-05-10 06:37:58","readingDateTimeLocal":"2022-05-09 23:37:58","latitude":47.29472222,"longitude":-122.4,"cellTowerAddress":"","tempC":9.559326171875,"humidity":66.38946533203125,"pressure":100252.2578125,"pM25":2.1463327407836914,"pM10":2.146331310272217,"pM1":2.0297021865844727,"vBattery":4.16921854019165,"cellSignal":-99,"fwVersion":"","aqi":8,"aqiLabel":"Good","calibratedPM25":0,"calibrationVersion":""},{"deploymentName":"Tacoma","deviceFriendlyName":"Crescent Heights Elementary School","msrDeviceNbr":"2189","readingDateTimeUTC":"2022-05-10 06:17:46","readingDateTimeLocal":"2022-05-09 23:17:46","latitude":47.29472222,"longitude":-122.4,"cellTowerAddress":"","tempC":9.791641235351562,"humidity":65.771484375,"pressure":100244.4453125,"pM25":6.4935197830200195,"pM10":10.59742259979248,"pM1":3.0128116607666016,"vBattery":4.170624732971191,"cellSignal":-100,"fwVersion":"","aqi":27,"aqiLabel":"Good","calibratedPM25":0,"calibrationVersion":""},{"deploymentName":"Tacoma","deviceFriendlyName":"Crescent Heights Elementary School","msrDeviceNbr":"2189","readingDateTimeUTC":"2022-05-10 05:57:34","readingDateTimeLocal":"2022-05-09 22:57:34","latitude":47.29472222,"longitude":-122.4,"cellTowerAddress":"","tempC":9.925155639648438,"humidity":66.00189208984375,"pressure":100233.171875,"pM25":2.7591848373413086,"pM10":4.071028232574463,"pM1":1.6094088554382324,"vBattery":4.171718597412109,"cellSignal":-100,"fwVersion":"","aqi":11,"aqiLabel":"Good","calibratedPM25":0,"calibrationVersion":""},{"deploymentName":"Tacoma","deviceFriendlyName":"Crescent Heights Elementary School","msrDeviceNbr":"2189","readingDateTimeUTC":"2022-05-10 05:37:22","readingDateTimeLocal":"2022-05-09 22:37:22","latitude":47.29472222,"longitude":-122.4,"cellTowerAddress":"","tempC":10.36041259765625,"humidity":64.34783935546875,"pressure":100218.4609375,"pM25":2.1116626262664795,"pM10":2.111661195755005,"pM1":1.9969159364700317,"vBattery":4.170781135559082,"cellSignal":-100,"fwVersion":"","aqi":8,"aqiLabel":"Good","calibratedPM25":0,"calibrationVersion":""},{"deploymentName":"Tacoma","deviceFriendlyName":"Crescent Heights Elementary School","msrDeviceNbr":"2189","readingDateTimeUTC":"2022-05-10 05:17:10","readingDateTimeLocal":"2022-05-09 22:17:10","latitude":47.29472222,"longitude":-122.4,"cellTowerAddress":"","tempC":10.547332763671875,"humidity":63.19427490234375,"pressure":100205.921875,"pM25":5.066010475158691,"pM10":6.855550289154053,"pM1":3.426798105239868,"vBattery":4.170312404632568,"cellSignal":-100,"fwVersion":"","aqi":21,"aqiLabel":"Good","calibratedPM25":0,"calibrationVersion":""},{"deploymentName":"Tacoma","deviceFriendlyName":"Crescent Heights Elementary School","msrDeviceNbr":"2189","readingDateTimeUTC":"2022-05-10 04:56:59","readingDateTimeLocal":"2022-05-09 21:56:59","latitude":47.29472222,"longitude":-122.4,"cellTowerAddress":"","tempC":10.7342529296875,"humidity":61.92169189453125,"pressure":100186.234375,"pM25":2.1534194946289062,"pM10":2.458872079849243,"pM1":1.8035979270935059,"vBattery":4.172187328338623,"cellSignal":-100,"fwVersion":"","aqi":8,"aqiLabel":"Good","calibratedPM25":0,"calibrationVersion":""},{"deploymentName":"Tacoma","deviceFriendlyName":"Crescent Heights Elementary School","msrDeviceNbr":"2189","readingDateTimeUTC":"2022-05-10 04:36:47","readingDateTimeLocal":"2022-05-09 21:36:47","latitude":47.29472222,"longitude":-122.4,"cellTowerAddress":"","tempC":11.10809326171875,"humidity":59.7869873046875,"pressure":100167.5,"pM25":2.009056806564331,"pM10":2.0090553760528564,"pM1":1.899885654449463,"vBattery":4.171249866485596,"cellSignal":-100,"fwVersion":"","aqi":8,"aqiLabel":"Good","calibratedPM25":0,"calibrationVersion":""},{"deploymentName":"Tacoma","deviceFriendlyName":"Crescent Heights Elementary School","msrDeviceNbr":"2189","readingDateTimeUTC":"2022-05-10 04:16:35","readingDateTimeLocal":"2022-05-09 21:16:35","latitude":47.29472222,"longitude":-122.4,"cellTowerAddress":"","tempC":11.73828125,"humidity":58.97979736328125,"pressure":100122.734375,"pM25":1.417586088180542,"pM10":1.4175851345062256,"pM1":1.340555191040039,"vBattery":4.172187328338623,"cellSignal":-100,"fwVersion":"","aqi":5,"aqiLabel":"Good","calibratedPM25":0,"calibrationVersion":""},{"deploymentName":"Tacoma","deviceFriendlyName":"Crescent Heights Elementary School","msrDeviceNbr":"2189","readingDateTimeUTC":"2022-05-10 03:56:24","readingDateTimeLocal":"2022-05-09 20:56:24","latitude":47.29472222,"longitude":-122.4,"cellTowerAddress":"","tempC":12.515335083007812,"humidity":57.0709228515625,"pressure":100091.6640625,"pM25":4.360080242156982,"pM10":7.499889373779297,"pM1":1.730101466178894,"vBattery":4.172343730926514,"cellSignal":-100,"fwVersion":"","aqi":18,"aqiLabel":"Good","calibratedPM25":0,"calibrationVersion":""},{"deploymentName":"Tacoma","deviceFriendlyName":"Crescent Heights Elementary School","msrDeviceNbr":"2189","readingDateTimeUTC":"2022-05-10 03:36:12","readingDateTimeLocal":"2022-05-09 20:36:12","latitude":47.29472222,"longitude":-122.4,"cellTowerAddress":"","tempC":13.046722412109375,"humidity":54.65240478515625,"pressure":100081.7109375,"pM25":1.3627362251281738,"pM10":1.3627352714538574,"pM1":1.2886857986450195,"vBattery":4.172343730926514,"cellSignal":-100,"fwVersion":"","aqi":5,"aqiLabel":"Good","calibratedPM25":0,"calibrationVersion":""},{"deploymentName":"Tacoma","deviceFriendlyName":"Crescent Heights Elementary School","msrDeviceNbr":"2189","readingDateTimeUTC":"2022-05-10 03:16:00","readingDateTimeLocal":"2022-05-09 20:16:00","latitude":47.29472222,"longitude":-122.4,"cellTowerAddress":"","tempC":13.783721923828125,"humidity":53.63616943359375,"pressure":100058.0078125,"pM25":0.7940592765808105,"pM10":0.7940587401390076,"pM1":0.7509104609489441,"vBattery":4.173593521118164,"cellSignal":-100,"fwVersion":"","aqi":3,"aqiLabel":"Good","calibratedPM25":0,"calibrationVersion":""},{"deploymentName":"Tacoma","deviceFriendlyName":"Crescent Heights Elementary School","msrDeviceNbr":"2189","readingDateTimeUTC":"2022-05-10 02:55:48","readingDateTimeLocal":"2022-05-09 19:55:48","latitude":47.29472222,"longitude":-122.4,"cellTowerAddress":"","tempC":14.042739868164062,"humidity":53.2623291015625,"pressure":100045.65625,"pM25":2.4473447799682617,"pM10":3.7433855533599854,"pM1":1.3265591859817505,"vBattery":4.17312479019165,"cellSignal":-100,"fwVersion":"","aqi":10,"aqiLabel":"Good","calibratedPM25":0,"calibrationVersion":""},{"deploymentName":"Tacoma","deviceFriendlyName":"Crescent Heights Elementary School","msrDeviceNbr":"2189","readingDateTimeUTC":"2022-05-10 02:35:37","readingDateTimeLocal":"2022-05-09 19:35:37","latitude":47.29472222,"longitude":-122.4,"cellTowerAddress":"","tempC":14.042739868164062,"humidity":52.801513671875,"pressure":100032.75,"pM25":2.855947494506836,"pM10":5.139088153839111,"pM1":0.9606258273124695,"vBattery":4.174218654632568,"cellSignal":-100,"fwVersion":"","aqi":11,"aqiLabel":"Good","calibratedPM25":0,"calibrationVersion":""},{"deploymentName":"Tacoma","deviceFriendlyName":"Crescent Heights Elementary School","msrDeviceNbr":"2189","readingDateTimeUTC":"2022-05-10 02:15:25","readingDateTimeLocal":"2022-05-09 19:15:25","latitude":47.29472222,"longitude":-122.4,"cellTowerAddress":"","tempC":14.165573120117188,"humidity":50.74920654296875,"pressure":99993.6796875,"pM25":4.969705104827881,"pM10":8.28939437866211,"pM1":2.169501543045044,"vBattery":4.175156116485596,"cellSignal":-100,"fwVersion":"","aqi":20,"aqiLabel":"Good","calibratedPM25":0,"calibrationVersion":""},{"deploymentName":"Tacoma","deviceFriendlyName":"Crescent Heights Elementary School","msrDeviceNbr":"2189","readingDateTimeUTC":"2022-05-10 01:55:13","readingDateTimeLocal":"2022-05-09 18:55:13","latitude":47.29472222,"longitude":-122.4,"cellTowerAddress":"","tempC":14.790420532226562,"humidity":49.5269775390625,"pressure":99978.703125,"pM25":1.2992596626281738,"pM10":1.299258828163147,"pM1":1.2286585569381714,"vBattery":4.174062252044678,"cellSignal":-100,"fwVersion":"","aqi":5,"aqiLabel":"Good","calibratedPM25":0,"calibrationVersion":""},{"deploymentName":"Tacoma","deviceFriendlyName":"Crescent Heights Elementary School","msrDeviceNbr":"2189","readingDateTimeUTC":"2022-05-10 01:35:02","readingDateTimeLocal":"2022-05-09 18:35:02","latitude":47.29472222,"longitude":-122.4,"cellTowerAddress":"","tempC":14.790420532226562,"humidity":50.018310546875,"pressure":99970.9609375,"pM25":5.278361797332764,"pM10":8.736929893493652,"pM1":2.3555376529693604,"vBattery":4.17312479019165,"cellSignal":-100,"fwVersion":"","aqi":21,"aqiLabel":"Good","calibratedPM25":0,"calibrationVersion":""},{"deploymentName":"Tacoma","deviceFriendlyName":"Crescent Heights Elementary School","msrDeviceNbr":"2189","readingDateTimeUTC":"2022-05-10 01:14:50","readingDateTimeLocal":"2022-05-09 18:14:50","latitude":47.29472222,"longitude":-122.4,"cellTowerAddress":"","tempC":15.287094116210938,"humidity":47.784423828125,"pressure":99974.6796875,"pM25":1.270482063293457,"pM10":1.2704812288284302,"pM1":1.2014446258544922,"vBattery":4.173593521118164,"cellSignal":-100,"fwVersion":"","aqi":5,"aqiLabel":"Good","calibratedPM25":0,"calibrationVersion":""},{"deploymentName":"Tacoma","deviceFriendlyName":"Crescent Heights Elementary School","msrDeviceNbr":"2189","readingDateTimeUTC":"2022-05-10 00:54:38","readingDateTimeLocal":"2022-05-09 17:54:38","latitude":47.29472222,"longitude":-122.4,"cellTowerAddress":"","tempC":15.72235107421875,"humidity":50.00457763671875,"pressure":99967.5078125,"pM25":0.7463773488998413,"pM10":0.7463768720626831,"pM1":0.7058196067810059,"vBattery":4.171562194824219,"cellSignal":-100,"fwVersion":"","aqi":3,"aqiLabel":"Good","calibratedPM25":0,"calibrationVersion":""},{"deploymentName":"Tacoma","deviceFriendlyName":"Crescent Heights Elementary School","msrDeviceNbr":"2189","readingDateTimeUTC":"2022-05-10 00:34:26","readingDateTimeLocal":"2022-05-09 17:34:26","latitude":47.29472222,"longitude":-122.4,"cellTowerAddress":"","tempC":15.5194091796875,"humidity":49.8046875,"pressure":99943.2890625,"pM25":3.2668886184692383,"pM10":5.376443862915039,"pM1":1.4815362691879272,"vBattery":4.175312519073486,"cellSignal":-101,"fwVersion":"","aqi":13,"aqiLabel":"Good","calibratedPM25":0,"calibrationVersion":""},{"deploymentName":"Tacoma","deviceFriendlyName":"Crescent Heights Elementary School","msrDeviceNbr":"2189","readingDateTimeUTC":"2022-05-10 00:14:14","readingDateTimeLocal":"2022-05-09 17:14:14","latitude":47.29472222,"longitude":-122.4,"cellTowerAddress":"","tempC":16.221694946289062,"humidity":48.66790771484375,"pressure":99937.0625,"pM25":2.765591859817505,"pM10":4.98256254196167,"pM1":0.9256128072738647,"vBattery":4.16921854019165,"cellSignal":-101,"fwVersion":"","aqi":11,"aqiLabel":"Good","calibratedPM25":0,"calibrationVersion":""},{"deploymentName":"Tacoma","deviceFriendlyName":"Crescent Heights Elementary School","msrDeviceNbr":"2189","readingDateTimeUTC":"2022-05-09 23:54:02","readingDateTimeLocal":"2022-05-09 16:54:02","latitude":47.29472222,"longitude":-122.4,"cellTowerAddress":"","tempC":16.307144165039062,"humidity":47.91107177734375,"pressure":99911,"pM25":7.681431770324707,"pM10":13.218966484069824,"pM1":3.043508768081665,"vBattery":4.170000076293945,"cellSignal":-100,"fwVersion":"","aqi":32,"aqiLabel":"Good","calibratedPM25":0,"calibrationVersion":""},{"deploymentName":"Tacoma","deviceFriendlyName":"Crescent Heights Elementary School","msrDeviceNbr":"2189","readingDateTimeUTC":"2022-05-09 23:33:51","readingDateTimeLocal":"2022-05-09 16:33:51","latitude":47.29472222,"longitude":-122.4,"cellTowerAddress":"","tempC":16.12823486328125,"humidity":48.944091796875,"pressure":99907.5,"pM25":1.7181153297424316,"pM10":2.8215653896331787,"pM1":0.7837420701980591,"vBattery":4.169687271118164,"cellSignal":-100,"fwVersion":"","aqi":7,"aqiLabel":"Good","calibratedPM25":0,"calibrationVersion":""},{"deploymentName":"Tacoma","deviceFriendlyName":"Crescent Heights Elementary School","msrDeviceNbr":"2189","readingDateTimeUTC":"2022-05-09 23:13:39","readingDateTimeLocal":"2022-05-09 16:13:39","latitude":47.29472222,"longitude":-122.4,"cellTowerAddress":"","tempC":16.336517333984375,"humidity":48.95782470703125,"pressure":99899.8203125,"pM25":0.6872918009757996,"pM10":0.6872913241386414,"pM1":0.6499446630477905,"vBattery":4.171718597412109,"cellSignal":-100,"fwVersion":"","aqi":2,"aqiLabel":"Good","calibratedPM25":0,"calibrationVersion":""},{"deploymentName":"Tacoma","deviceFriendlyName":"Crescent Heights Elementary School","msrDeviceNbr":"2189","readingDateTimeUTC":"2022-05-09 22:53:27","readingDateTimeLocal":"2022-05-09 15:53:27","latitude":47.29472222,"longitude":-122.4,"cellTowerAddress":"","tempC":16.1602783203125,"humidity":54.13360595703125,"pressure":99894.34375,"pM25":1.873970627784729,"pM10":1.8739694356918335,"pM1":1.7721400260925293,"vBattery":4.166874885559082,"cellSignal":-100,"fwVersion":"","aqi":7,"aqiLabel":"Good","calibratedPM25":0,"calibrationVersion":""},{"deploymentName":"Tacoma","deviceFriendlyName":"Crescent Heights Elementary School","msrDeviceNbr":"2189","readingDateTimeUTC":"2022-05-09 22:33:15","readingDateTimeLocal":"2022-05-09 15:33:15","latitude":47.29472222,"longitude":-122.4,"cellTowerAddress":"","tempC":15.03875732421875,"humidity":56.77947998046875,"pressure":99897.2890625,"pM25":1.2653719186782837,"pM10":1.8093492984771729,"pM1":0.7820106148719788,"vBattery":4.168281078338623,"cellSignal":-101,"fwVersion":"","aqi":5,"aqiLabel":"Good","calibratedPM25":0,"calibrationVersion":""},{"deploymentName":"Tacoma","deviceFriendlyName":"Crescent Heights Elementary School","msrDeviceNbr":"2189","readingDateTimeUTC":"2022-05-09 22:13:03","readingDateTimeLocal":"2022-05-09 15:13:03","latitude":47.29472222,"longitude":-122.4,"cellTowerAddress":"","tempC":13.575439453125,"humidity":55.88226318359375,"pressure":99916.8828125,"pM25":1.659777045249939,"pM10":2.674407482147217,"pM1":0.7962689995765686,"vBattery":4.172343730926514,"cellSignal":-100,"fwVersion":"","aqi":6,"aqiLabel":"Good","calibratedPM25":0,"calibrationVersion":""},{"deploymentName":"Tacoma","deviceFriendlyName":"Crescent Heights Elementary School","msrDeviceNbr":"2189","readingDateTimeUTC":"2022-05-09 21:52:51","readingDateTimeLocal":"2022-05-09 14:52:51","latitude":47.29472222,"longitude":-122.4,"cellTowerAddress":"","tempC":13.3404541015625,"humidity":52.05841064453125,"pressure":99881.1953125,"pM25":2.8286449909210205,"pM10":4.412941932678223,"pM1":1.4674402475357056,"vBattery":4.16921854019165,"cellSignal":-99,"fwVersion":"","aqi":11,"aqiLabel":"Good","calibratedPM25":0,"calibrationVersion":""},{"deploymentName":"Tacoma","deviceFriendlyName":"Crescent Heights Elementary School","msrDeviceNbr":"2189","readingDateTimeUTC":"2022-05-09 21:32:40","readingDateTimeLocal":"2022-05-09 14:32:40","latitude":47.29472222,"longitude":-122.4,"cellTowerAddress":"","tempC":15.404586791992188,"humidity":44.08721923828125,"pressure":99850.3671875,"pM25":1.0959250926971436,"pM10":1.4455766677856445,"pM1":0.7698805332183838,"vBattery":4.168124675750732,"cellSignal":-100,"fwVersion":"","aqi":4,"aqiLabel":"Good","calibratedPM25":0,"calibrationVersion":""},{"deploymentName":"Tacoma","deviceFriendlyName":"Crescent Heights Elementary School","msrDeviceNbr":"2189","readingDateTimeUTC":"2022-05-09 21:12:28","readingDateTimeLocal":"2022-05-09 14:12:28","latitude":47.29472222,"longitude":-122.4,"cellTowerAddress":"","tempC":18.299179077148438,"humidity":37.63885498046875,"pressure":99819.4140625,"pM25":4.606109619140625,"pM10":7.448915004730225,"pM1":2.18912672996521,"vBattery":4.167655944824219,"cellSignal":-101,"fwVersion":"","aqi":19,"aqiLabel":"Good","calibratedPM25":0,"calibrationVersion":""},{"deploymentName":"Tacoma","deviceFriendlyName":"Crescent Heights Elementary School","msrDeviceNbr":"2189","readingDateTimeUTC":"2022-05-09 20:52:16","readingDateTimeLocal":"2022-05-09 13:52:16","latitude":47.29472222,"longitude":-122.4,"cellTowerAddress":"","tempC":21.2872314453125,"humidity":33.013916015625,"pressure":99810.2578125,"pM25":3.4051692485809326,"pM10":5.643086910247803,"pM1":1.5144703388214111,"vBattery":4.162656307220459,"cellSignal":-100,"fwVersion":"","aqi":14,"aqiLabel":"Good","calibratedPM25":0,"calibrationVersion":""},{"deploymentName":"Tacoma","deviceFriendlyName":"Crescent Heights Elementary School","msrDeviceNbr":"2189","readingDateTimeUTC":"2022-05-09 20:32:04","readingDateTimeLocal":"2022-05-09 13:32:04","latitude":47.29472222,"longitude":-122.4,"cellTowerAddress":"","tempC":22.758560180664062,"humidity":33.819580078125,"pressure":99805.0546875,"pM25":0.6798972487449646,"pM10":0.6798967719078064,"pM1":0.6429519653320312,"vBattery":4.163749694824219,"cellSignal":-101,"fwVersion":"","aqi":2,"aqiLabel":"Good","calibratedPM25":0,"calibrationVersion":""},{"deploymentName":"Tacoma","deviceFriendlyName":"Crescent Heights Elementary School","msrDeviceNbr":"2189","readingDateTimeUTC":"2022-05-09 20:11:52","readingDateTimeLocal":"2022-05-09 13:11:52","latitude":47.29472222,"longitude":-122.4,"cellTowerAddress":"","tempC":23.631744384765625,"humidity":33.31146240234375,"pressure":99810.984375,"pM25":1.528624415397644,"pM10":2.3262970447540283,"pM1":0.8376002907752991,"vBattery":4.162499904632568,"cellSignal":-101,"fwVersion":"","aqi":6,"aqiLabel":"Good","calibratedPM25":0,"calibrationVersion":""},{"deploymentName":"Tacoma","deviceFriendlyName":"Crescent Heights Elementary School","msrDeviceNbr":"2189","readingDateTimeUTC":"2022-05-09 19:51:41","readingDateTimeLocal":"2022-05-09 12:51:41","latitude":47.29472222,"longitude":-122.4,"cellTowerAddress":"","tempC":23.778610229492188,"humidity":34.4573974609375,"pressure":99797.3671875,"pM25":0.6903459429740906,"pM10":0.6903455257415771,"pM1":0.6528329253196716,"vBattery":4.163906097412109,"cellSignal":-100,"fwVersion":"","aqi":2,"aqiLabel":"Good","calibratedPM25":0,"calibrationVersion":""},{"deploymentName":"Tacoma","deviceFriendlyName":"Crescent Heights Elementary School","msrDeviceNbr":"2189","readingDateTimeUTC":"2022-05-09 19:31:29","readingDateTimeLocal":"2022-05-09 12:31:29","latitude":47.29472222,"longitude":-122.4,"cellTowerAddress":"","tempC":23.49822998046875,"humidity":35.247802734375,"pressure":99811.6328125,"pM25":3.5412323474884033,"pM10":6.56102180480957,"pM1":1.0472246408462524,"vBattery":4.163280963897705,"cellSignal":-101,"fwVersion":"","aqi":14,"aqiLabel":"Good","calibratedPM25":0,"calibrationVersion":""},{"deploymentName":"Tacoma","deviceFriendlyName":"Crescent Heights Elementary School","msrDeviceNbr":"2189","readingDateTimeUTC":"2022-05-09 19:11:17","readingDateTimeLocal":"2022-05-09 12:11:17","latitude":47.29472222,"longitude":-122.4,"cellTowerAddress":"","tempC":23.257904052734375,"humidity":35.89324951171875,"pressure":99796.2421875,"pM25":3.3385069370269775,"pM10":6.09789514541626,"pM1":1.0539836883544922,"vBattery":4.162812232971191,"cellSignal":-100,"fwVersion":"","aqi":13,"aqiLabel":"Good","calibratedPM25":0,"calibrationVersion":""},{"deploymentName":"Tacoma","deviceFriendlyName":"Crescent Heights Elementary School","msrDeviceNbr":"2189","readingDateTimeUTC":"2022-05-09 18:51:05","readingDateTimeLocal":"2022-05-09 11:51:05","latitude":47.29472222,"longitude":-122.4,"cellTowerAddress":"","tempC":22.25921630859375,"humidity":38.10272216796875,"pressure":99803.0859375,"pM25":1.1357616186141968,"pM10":1.6023584604263306,"pM1":0.7184202671051025,"vBattery":4.164687633514404,"cellSignal":-100,"fwVersion":"","aqi":4,"aqiLabel":"Good","calibratedPM25":0,"calibrationVersion":""},{"deploymentName":"Tacoma","deviceFriendlyName":"Crescent Heights Elementary School","msrDeviceNbr":"2189","readingDateTimeUTC":"2022-05-09 18:30:54","readingDateTimeLocal":"2022-05-09 11:30:54","latitude":47.29472222,"longitude":-122.4,"cellTowerAddress":"","tempC":20.510177612304688,"humidity":41.217041015625,"pressure":99807.7109375,"pM25":1.5531785488128662,"pM10":2.48872971534729,"pM1":0.755734384059906,"vBattery":4.1640625,"cellSignal":-100,"fwVersion":"","aqi":6,"aqiLabel":"Good","calibratedPM25":0,"calibrationVersion":""},{"deploymentName":"Tacoma","deviceFriendlyName":"Crescent Heights Elementary School","msrDeviceNbr":"2189","readingDateTimeUTC":"2022-05-09 18:10:42","readingDateTimeLocal":"2022-05-09 11:10:42","latitude":47.29472222,"longitude":-122.4,"cellTowerAddress":"","tempC":19.025497436523438,"humidity":41.30859375,"pressure":99797.3125,"pM25":1.43715238571167,"pM10":2.1741294860839844,"pM1":0.7973597645759583,"vBattery":4.167187213897705,"cellSignal":-100,"fwVersion":"","aqi":5,"aqiLabel":"Good","calibratedPM25":0,"calibrationVersion":""},{"deploymentName":"Tacoma","deviceFriendlyName":"Crescent Heights Elementary School","msrDeviceNbr":"2189","readingDateTimeUTC":"2022-05-09 17:50:30","readingDateTimeLocal":"2022-05-09 10:50:30","latitude":47.29472222,"longitude":-122.4,"cellTowerAddress":"","tempC":17.30316162109375,"humidity":46.76055908203125,"pressure":99792.8984375,"pM25":0.654850423336029,"pM10":0.6548499464988708,"pM1":0.619266152381897,"vBattery":4.167031288146973,"cellSignal":-100,"fwVersion":"","aqi":2,"aqiLabel":"Good","calibratedPM25":0,"calibrationVersion":""}]